dastyor/__init__.py
dastyor/app.py
dastyor/cli.py
dastyor/custom_commands.py
dastyor/middleware.py
dastyor/response.py
dastyor/serve.py
dastyor/wsgi.py
dastyor-0.1.9.dist-info/LICENSE
dastyor-0.1.9.dist-info/METADATA
dastyor-0.1.9.dist-info/WHEEL
dastyor-0.1.9.dist-info/entry_points.txt
dastyor-0.1.9.dist-info/top_level.txt
dastyor-0.1.9.dist-info/RECORD
